{
  "pipeline_name": "Baseline_C",
  "pipeline_slug": "Baseline_C",
  "subset_index": 1,
  "subset_count": 5,
  "saved_at": "2026-04-29T20:42:56",
  "model": {
    "class_name": "QNN_Baseline_PCA",
    "module": "__main__",
    "repr": "QNN_Baseline_PCA(\n  (qnn_pytorch_layer): TorchConnector()\n  (classical_head): Linear(in_features=4096, out_features=10, bias=True)\n  (softmax): LogSoftmax(dim=-1)\n)"
  },
  "report_context": {
    "title": "EXPERIMENTAL PROTOCOL REPORT",
    "dataset_name": "MNIST digits stratified",
    "classifier_name": "PCA + ZZFeatureMap + QNN",
    "model_architecture": "16x16 grayscale -> Flatten(256) -> PCA(num_qubits) -> ZZFeatureMap(reps=1) -> VQC[RX-RY-RZ x num_layers + brickwork CX] -> SamplerQNN -> Linear(2**num_qubits, num_classes) -> LogSoftmax",
    "subset_name": "1/5",
    "split_sizes": {
      "train": 921,
      "val": 231,
      "test": 288
    },
    "training_setup": {
      "epochs": 10,
      "batch_size": 16,
      "device": "cpu",
      "qnn_lr": 0.001,
      "head_lr": 0.01
    },
    "model_setup": {
      "num_classes": 10,
      "num_qubits": 12,
      "num_layers": 1
    }
  }
}